{
  "data": [
      {
        "id": 1,
        "name" : "fruits",
        "list": [
          {
            "id": 1,
            "text": "orange",
            "filename": "notific.mp3"
          },
          {
            "id": 2,
            "text": "orange2",
            "filename": "notific.mp3"
          },
          {
            "id": 3,
            "text": "orange3",
            "filename": "notific.mp3"
          },
          {
            "id": 4,
            "text": "orange4",
            "filename": "orientation.mp3"
          },
          {
            "id": 5,
            "text": "orange5",
            "filename": "orientation.mp3"
          }
        ]
      },
      {
        "id": 2,
        "name" : "vegetables",
        "list": [
          {
            "id": 6,
            "text": "tomatoes"
          },
          {
            "id": 7,
            "text": "tomatoes2"
          },
          {
            "id": 8,
            "text": "tomatoes"
          }
        ]
      }
    ],
  "status" : "200"
}